LICENSE
MANIFEST.in
README.md
setup.py
src/chattemplate/__init__.py
src/chattemplate/cli.py
src/chattemplate/log.py
src/chattemplate/registry.py
src/chattemplate.egg-info/PKG-INFO
src/chattemplate.egg-info/SOURCES.txt
src/chattemplate.egg-info/dependency_links.txt
src/chattemplate.egg-info/entry_points.txt
src/chattemplate.egg-info/requires.txt
src/chattemplate.egg-info/top_level.txt
src/chattemplate/bot/__init__.py
src/chattemplate/bot/chat_with_arxiv.py
src/chattemplate/bot/simple_chat.py
src/chattemplate/bot/utils.py
src/chattemplate/llm/__init__.py
src/chattemplate/llm/fake.py
src/chattemplate/llm/huggingface.py
src/chattemplate/llm/openai.py
src/chattemplate/llm/utils.py
src/chattemplate/tool/__init__.py
src/chattemplate/tool/arxiv.py
src/chattemplate/tool/utils.py