Metadata-Version: 2.1
Name: chattemplate
Version: 0.1.0.dev4
Summary: ChatTemplate
Home-page: https://github.com/mccpr/chattemplate
Author: ericmccpr
Author-email: ericweb781@gmail.com
Classifier: Programming Language :: Python :: 3
Classifier: License :: OSI Approved :: MIT License
Classifier: Operating System :: OS Independent
Requires-Python: >=3.8
License-File: LICENSE
Requires-Dist: gradio
Requires-Dist: transformers
Requires-Dist: openai
Requires-Dist: sentencepiece
Requires-Dist: protobuf
Requires-Dist: accelerate
